bin/puffmatic-net
bin/puffmatic-umount
bin/puffmatic-usb
puffmatic/__main__.py
puffmatic/disklabel.py
puffmatic/getimg.py
puffmatic/mirror.py
puffmatic/patchimg.py
puffmatic/response.py
puffmatic/sets.py
puffmatic/utils.py
puffmatic/tests/__init__.py
puffmatic/tests/conftest.py
puffmatic/tests/test_conftest.py
puffmatic/tests/test_disklabel.py
puffmatic/tests/test_getimg.py
puffmatic/tests/test_init.py
puffmatic/tests/test_main.py
puffmatic/tests/test_mirror.py
puffmatic/tests/test_patchimg.py
puffmatic/tests/test_response.py
puffmatic/tests/test_sets.py
puffmatic/tests/test_utils.py
puffmatic-0.1.0a4.data/scripts/puffmatic-net
puffmatic-0.1.0a4.data/scripts/puffmatic-umount
puffmatic-0.1.0a4.data/scripts/puffmatic-usb
puffmatic-0.1.0a4.dist-info/licenses/LICENSE.txt
puffmatic-0.1.0a4.dist-info/METADATA
puffmatic-0.1.0a4.dist-info/WHEEL
puffmatic-0.1.0a4.dist-info/top_level.txt
puffmatic-0.1.0a4.dist-info/RECORD
