Metadata-Version: 2.4
Name: puffmatic
Version: 0.1.0a4
Summary: Quickly generate files and installer images for unattended OpenBSD installation.
Author-email: Chris narkiewicz <hello@ezaquarii.com>
License: BSD-3-Clause
Project-URL: Homepage, https://github.com/ezaquarii/puffmatic/
Project-URL: Documentation, https://github.com/ezaquarii/puffmatic/
Project-URL: Repository, https://github.com/ezaquarii/puffmatic.git
Project-URL: Issues, https://github.com/ezaquarii/puffmatic/issues
Project-URL: Changelog, https://github.com/ezaquarii/puffmatic/blob/master/CHANGELOG.md
Keywords: openbsd,autoinstall,sysutil
Classifier: Intended Audience :: Developers
Classifier: Topic :: Software Development :: Build Tools
Classifier: Programming Language :: Python :: 3
Requires-Python: >=3.12
License-File: LICENSE.txt
Requires-Dist: Jinja2
Requires-Dist: PyYAML
Provides-Extra: dev
Requires-Dist: build; extra == "dev"
Requires-Dist: debugpy; extra == "dev"
Requires-Dist: pytest; extra == "dev"
Requires-Dist: pytest-cov; extra == "dev"
Provides-Extra: pub
Requires-Dist: twine; extra == "pub"
Dynamic: license-file
